the_census/__init__.py
the_census/_api/__init__.py
the_census/_api/fetch.py
the_census/_api/interface.py
the_census/_api/models.py
the_census/_api/serialization.py
the_census/_client.py
the_census/_config.py
the_census/_data_transformation/__init__.py
the_census/_data_transformation/interface.py
the_census/_data_transformation/service.py
the_census/_exceptions.py
the_census/_geographies/__init__.py
the_census/_geographies/interface.py
the_census/_geographies/models.py
the_census/_geographies/service.py
the_census/_helpers.py
the_census/_persistence/__init__.py
the_census/_persistence/interface.py
the_census/_persistence/onDisk.py
the_census/_stats/__init__.py
the_census/_stats/interface.py
the_census/_stats/service.py
the_census/_utils/__init__.py
the_census/_utils/chunk.py
the_census/_utils/clean_variable_name.py
the_census/_utils/log/__init__.py
the_census/_utils/log/configureLogger.py
the_census/_utils/log/factory.py
the_census/_utils/log/filters.py
the_census/_utils/timer.py
the_census/_utils/unique.py
the_census/_variables/models.py
the_census/_variables/repository/__init__.py
the_census/_variables/repository/interface.py
the_census/_variables/repository/models.py
the_census/_variables/repository/service.py
the_census/_variables/search/__init__.py
the_census/_variables/search/interface.py
the_census/_variables/search/service.py
the_census/census.py
the_census-2.1.2.dist-info/LICENSE
the_census-2.1.2.dist-info/WHEEL
the_census-2.1.2.dist-info/METADATA
the_census-2.1.2.dist-info/RECORD
