Metadata-Version: 2.1
Name: the-census
Version: 2.1.2
Summary: Tool to get and query US Census data
Home-page: https://github.com/drawjk705/us-stats/
Keywords: US,census
Author: Joel Krim
Author-email: drawjk705@gmail.com
Requires-Python: >=3.9,<4.0
Classifier: Programming Language :: Python :: 3
Classifier: Programming Language :: Python :: 3.9
Classifier: Topic :: Software Development :: Libraries :: Python Modules
Requires-Dist: pandas (>=1.2.0,<2.0.0)
Requires-Dist: punq (>=0.4.1,<0.5.0)
Requires-Dist: python-dotenv (>=0.15.0,<0.16.0)
Requires-Dist: requests (>=2.25.1,<3.0.0)
Requires-Dist: tqdm (>=4.55.1,<5.0.0)
Project-URL: Repository, https://github.com/drawjk705/us-stats/
